{"quotes": [{"lines": [{"text": "[to Patricia]\nSay, baby, I'm for yuh. My face hasn't been so red since I went to my first burlesque show.", "character": "Dwight Wilson", "characterId": "nm0260020"}]}, {"lines": [{"text": "Ah, that Valerie was delirious!", "character": "Police Chief John F. O'Hara", "characterId": "nm0002177"}, {"text": "It wouldn't be the first time a million dollars made a man delirious", "character": "Dr. Paul Cornelius", "characterId": "nm0645941"}]}, {"lines": [{"text": "A man might make many compromises with his integrity for... ah... oh... say... a half million dollars.", "character": "Horace Merrick", "characterId": "nm0226502"}]}]}