{"quotes": [{"lines": [{"text": "[after being slapped]\nIf you ever do that again, I'm gonna pull your eyeballs outta your head and eat 'em.", "character": "Danny", "characterId": "nm0363936"}]}, {"lines": [{"text": "You're on our turf, scum fuck.", "character": "Goose", "characterId": "nm0885666"}]}, {"lines": [{"text": "Fuck your noise!", "character": "Goose", "characterId": "nm0885666"}]}, {"lines": [{"text": "You oughta get laid more often, Keith, you'd be less of a fuckhead.", "character": "Goose", "characterId": "nm0885666"}, {"text": "Shit, I fuck like a bunny.", "character": "Keith", "characterId": "nm0908133"}, {"text": "Yeah, quick.", "character": "Goose", "characterId": "nm0885666"}]}, {"lines": [{"text": "I don't need your voodoo magic around my neck!", "character": "Goose", "characterId": "nm0885666"}]}, {"lines": [{"text": "Christy is dead.", "character": "Goose", "characterId": "nm0885666"}, {"text": "Did you kill her?", "character": "Christy's sister", "characterId": "nm0496946"}, {"text": "No... I loved her.", "character": "Goose", "characterId": "nm0885666"}]}]}