{"quotes": [{"lines": [{"text": "[first lines]", "character": null, "characterId": null}, {"text": "Hello. There's a lot of people out there! How ya doin'? One moment, please.", "character": "Frank Zappa", "characterId": "nm0953261"}]}, {"lines": [{"text": "Now do me a favor and sit down - okay? Tonight we're gonna do a very long show - I don't want your legs to get tired, so move back, and sit down and be comfortable. Do it, do it. I don't want to have any problems with people getting mashed here in the front, so please relax.", "character": "Frank Zappa", "characterId": "nm0953261"}]}]}