{"quotes": [{"lines": [{"text": "You mean you were a civilian once?", "character": "Sgt. Joe Peterson", "characterId": "nm0000034"}, {"text": "Oh, if you consider schoolteachers civilians.", "character": "Lt. Eleanor MacKay", "characterId": "nm0647970"}, {"text": "You, honest?", "character": "Sgt. Joe Peterson", "characterId": "nm0000034"}, {"text": "Mm-hmm.", "character": "Lt. Eleanor MacKay", "characterId": "nm0647970"}, {"text": "Well, and me without an apple!", "character": "Sgt. Joe Peterson", "characterId": "nm0000034"}]}]}