{"quotes": [{"lines": [{"text": "[while getting her breasts/chest massaged]\nUnlike you I wasn't given anything. I am not talking about money not just. Everything I own. Everything I have I have. I have earned. So don't tell me I am wrong don't tell me I am immoral. Because I choose to make something of my life and you didn't. I mean shouldn't a man your age be something.", "character": "Nina", "characterId": "nm0000211"}, {"text": "I know you have made something of your life. I am just asking you what that is.", "character": "Fitch", "characterId": "nm0000986"}]}, {"lines": [{"text": "[while getting her chest/breasts massaged and talking to Finch]\nNo you're not.", "character": "Nina", "characterId": "nm0000211"}]}]}