{"quotes": [{"lines": [{"text": "Sex is healthy, don't you think? And necessary?", "character": "Guy", "characterId": "nm0000352"}, {"text": "Why is that?", "character": "Camera", "characterId": "nm0204706"}, {"text": "Well, to put up with all this shit around us, y'know? I mean, y'know, it's good to get fucked. That's why when it's really good, people say, y'know, \"She fucked my brains out,\" or \"he fucked my brains out.\" You wanna get your brains fucked out?", "character": "Guy", "characterId": "nm0000352"}]}, {"lines": [{"text": "I remember the first time I tried to masturbate. I was in my bed and I was all alone in the dark, and, um, there were these next-door neighbors, these two kids I used to play with, and their mother used to water the lawn in this bikini, y'know, right in the front yard. Y'know, her name was Tracy. She was this, like, incredible, kind of southern belle woman, with beautiful breasts. And I remember I was laying on my stomach and rocking back and forth, getting an adolescent erection, and I guess that if I was an adult I would've cum, but instead I got this incredibly horrible pain in my penis. And it hurt for a long time, and I always thought that that was the result of being turned on to my next-door neighbors' mother.", "character": "Guy", "characterId": "nm0000352"}]}, {"lines": [{"text": "I wish that I was in love. I miss love.", "character": "Guy", "characterId": "nm0000352"}]}]}