{"quotes": [{"lines": [{"text": "Adam, where'd you find those two oafs?", "character": "Chatsworth", "characterId": "nm0043088"}, {"text": "Oh, they're not oafs, Jack. They would require practice to become oafs.", "character": "Adam Worth", "characterId": "nm0000323"}]}, {"lines": [{"text": "[singing]\nHe's not the real Prince Herbert. I am!", "character": "Harry Dighby", "characterId": "nm0001001"}]}, {"lines": [{"text": "I need a favor, Mr. Durgom. I want these two clods assigned to the nitro detail, as soon as possible.", "character": "Adam Worth", "characterId": "nm0000323"}, {"text": "You mean permanently, sir?", "character": "Warden Durgom", "characterId": "nm0949350"}, {"text": "No, Mr. Durgom. Not permanently. Just until they die!", "character": "Adam Worth", "characterId": "nm0000323"}]}]}