{"quotes": [{"lines": [{"text": "Happy Halloween, you filthy old hag!", "character": "Mark", "characterId": "nm0709527"}]}, {"lines": [{"text": "I hate Halloween. It's dumb.", "character": "Young Mark", "characterId": "nm1879370"}]}, {"lines": [{"text": "You have to come out now. There's no way out, filthy little pig!", "character": "Mark", "characterId": "nm0709527"}]}, {"lines": [{"text": "Happy halloween, gook!", "character": "Mark", "characterId": "nm0709527"}]}, {"lines": [{"text": "War is hell. The gooks are out!", "character": "Mark", "characterId": "nm0709527"}]}, {"lines": [{"text": "Hold up there, Cha boy!", "character": "Mark", "characterId": "nm0709527"}]}]}