{"quotes": [{"lines": [{"text": "[grabbing the microphone at a Bar-Mitzvah]", "character": null, "characterId": null}, {"text": "You and your guests stink!", "character": "Emilio", "characterId": "nm0246299"}]}, {"lines": [{"text": "I want to destroy him in his father's eyes!", "character": "Roland Bettoun", "characterId": "nm0201462"}]}, {"lines": [{"text": "It's your hatred that has caused this death.", "character": "Raymond Bettoun", "characterId": "nm0359894"}]}, {"lines": [{"text": "There isn't a twenty-dollar bill in Miami that doesn't have a little coke on it.", "character": "Maurice Bettoun", "characterId": "nm0006939"}]}, {"lines": [{"text": "I should have known - never work with Jews.", "character": "Pasco Meisner", "characterId": "nm0000686"}]}, {"lines": [{"text": "I'm gonna give you three days, but if you don't bring me the coke, I'll hand you your son's head in a plastic garbage bag.", "character": "Pasco Meisner", "characterId": "nm0000686"}]}, {"lines": [{"text": "God's clock isn't set like ours is.", "character": null, "characterId": null}]}, {"lines": [{"text": "Thank you Maurice, you forgot to invite me but I'll stay anyways.", "character": "Emilio", "characterId": "nm0246299"}]}, {"lines": [{"text": "To all those who left us may they die twice!", "character": "Sammy", "characterId": "nm0208600"}]}, {"lines": [{"text": "Pasco, your the one who is going to die, in spite of all your guards.", "character": "Raymond Bettoun", "characterId": "nm0359894"}, {"text": "I'm Gonna Die? We gotta scoop here, whos gonna kill me you?", "character": "Pasco Meisner", "characterId": "nm0000686"}, {"text": "Could be, yes", "character": "Raymond Bettoun", "characterId": "nm0359894"}, {"text": "Amigo, I've looked death in the face a dozen times. Didn't look like you.", "character": "Pasco Meisner", "characterId": "nm0000686"}]}, {"lines": [{"text": "Eli, it looks you put on weight.", "character": "Roland Bettoun", "characterId": "nm0201462"}, {"text": "I don't think so.", "character": "Eli Bettoun", "characterId": "nm0786957"}, {"text": "Oh well, it looks like it.", "character": "Roland Bettoun", "characterId": "nm0201462"}]}]}