{"quotes": [{"lines": [{"text": "Make sure you're not involved, woncha? Cos I'll put a tool right in your belly!", "character": "John McVicar", "characterId": "nm0002032"}]}, {"lines": [{"text": "[Terry is joking to the other prisoners about the Durham Light Infantry]", "character": null, "characterId": null}, {"text": "They found a whole barrack load of them stuck up each other... Sunk to the nuts, they were. They're gonna rename them - the Durham Bumpers. Ah, they do love an arsehole, these Geordies!", "character": "Terry Stokes", "characterId": "nm0355363"}, {"text": "[laughter]", "character": null, "characterId": null}]}, {"lines": [{"text": "[Prisoner Cody is brought from the secure wing for dinner]", "character": null, "characterId": null}, {"text": "Sex case! Sex case! Hang him, hang him, hang him!", "character": "Terry Stokes", "characterId": "nm0355363"}, {"text": "[joining in from their cells]\nSex case! Sex case! Hang him, hang him, hang him!", "character": null, "characterId": null}, {"text": "[louder]\nSex case! Sex case! Hang him, hang him, hang him!", "character": null, "characterId": null}, {"text": "[louder still]\nSex case! Sex case! Hang him, hang him, hang him, hang him, hang him, hang him!", "character": null, "characterId": null}, {"text": "[shouting]\nHang him, hang him, hang him, hang him, hang him, hang him!", "character": null, "characterId": null}]}, {"lines": [{"text": "I suppose you think you got the better of us there. But just remember, kidder, you're in for ten years.", "character": "Prison Officer Rabies Pendel", "characterId": "nm0371304"}, {"text": "Yeah, that's right, Mr. Pendel. But you're in for life, ain't yer?", "character": "Terry Stokes", "characterId": "nm0355363"}]}]}