{"quotes": [{"lines": [{"text": "Now, one good turn deserves another. Could you point out to me the shortest route to the La Brea Tar Pits in Los Ahn-galays?", "character": "Bugs Bunny", "characterId": "nm0000305"}, {"text": "[confused]\nLa Brea Tar Pits?", "character": "MacRory", "characterId": "nm0000305"}, {"text": "[suddenly realizing, MacRory runs off and quickly returns with a blunderbuss, pointing it at Bugs' back]", "character": null, "characterId": null}, {"text": "There are no La Brea Tar Pits in Scotland!", "character": "MacRory", "characterId": "nm0000305"}, {"text": "Scotland? Eh, what's up, MacDoc?", "character": "Bugs Bunny", "characterId": "nm0000305"}, {"text": "[Bugs quickly departs]", "character": null, "characterId": null}]}, {"lines": [{"text": "[picking up a spent bullet from his gun and loading it back in]\nIt's been in the family for years.", "character": "MacRory", "characterId": "nm0000305"}]}, {"lines": [{"text": "[disguised as aged Scotsman]\nSo, MacR-r-rory, poaching on my pr-r-roperty! I'm displeased, MacR-r-rory. You shouldnae shoot my r-r-r-rabbits.", "character": "Bugs Bunny", "characterId": "nm0000305"}, {"text": "Yon bonnie rabbit dinna belong to you.", "character": "MacRory", "characterId": "nm0000305"}, {"text": "It dinna?", "character": "Bugs Bunny", "characterId": "nm0000305"}, {"text": "No, it dinna!", "character": "MacRory", "characterId": "nm0000305"}, {"text": "Wanna bet?", "character": "Bugs Bunny", "characterId": "nm0000305"}, {"text": "at games.", "character": "MacRory", "characterId": "nm0000305"}, {"text": "Games?", "character": "Bugs Bunny", "characterId": "nm0000305"}, {"text": "[Bugs sets up a card table and deals cards]", "character": null, "characterId": null}, {"text": "Okay, pigeon, sit down.", "character": "Bugs Bunny", "characterId": "nm0000305"}, {"text": "No, no, we dinna play that game.", "character": "MacRory", "characterId": "nm0000305"}, {"text": "[slightly surprised]\nIs there another one?", "character": "Bugs Bunny", "characterId": "nm0000305"}, {"text": "[pulling out two bags of golf clubs]\nGolf!", "character": "MacRory", "characterId": "nm0000305"}, {"text": "Golf?", "character": "Bugs Bunny", "characterId": "nm0000305"}, {"text": "Aye, golf. Choose your weapons.", "character": "MacRory", "characterId": "nm0000305"}, {"text": "Have it your way, Mac, but don't you get a little tired running them eighteen bases?", "character": "Bugs Bunny", "characterId": "nm0000305"}]}, {"lines": [{"text": "[MacRory is about to drive his golf ball]\nFore!", "character": "Bugs Bunny", "characterId": "nm0000305"}, {"text": "Four? Three and a half.", "character": "MacRory", "characterId": "nm0000305"}]}]}