{"quotes": [{"lines": [{"text": "Do you know where you are, Bartolome? I'll tell you where you are. You are about to enter Hell, Bartolome, HELL!... The netherworld.The infernal region, The Abode of the Damned... The place of torment. Pandemonium. Abbadon. Tophet. Gehenna. Naraka. THE PIT!... And the pendulum.", "character": "Don Nicholas Medina", "characterId": "nm0001637"}]}, {"lines": [{"text": "You will die in agony. Die!", "character": "Don Nicholas Medina", "characterId": "nm0001637"}]}, {"lines": [{"text": "The atmosphere is heavy in here.", "character": "Don Nicholas Medina", "characterId": "nm0001637"}, {"text": "[opens the curtains in Elizabeth's room]", "character": null, "characterId": null}, {"text": "Why have you brought me here?", "character": "Francis", "characterId": "nm0449734"}, {"text": "It is her room, sir. I've had it kept exactly as she left it.", "character": "Don Nicholas Medina", "characterId": "nm0001637"}]}, {"lines": [{"text": "[shouting Don Medina's name causing him to fall down the stairs]\nNicholas!", "character": "Elizabeth", "characterId": "nm0824489"}]}, {"lines": [{"text": "[after Nicholas has fallen down the stairs and appears to have died]\nI told you to wait.", "character": "Doctor Leon", "characterId": "nm0136147"}, {"text": "I couldn't.", "character": "Elizabeth", "characterId": "nm0824489"}, {"text": "[she and Dr. Leon kiss]", "character": null, "characterId": null}, {"text": "What about my brother?", "character": "Elizabeth", "characterId": "nm0824489"}, {"text": "He's supposed to leave in the morning , but now... why couldn't you wait one more day?", "character": "Doctor Leon", "characterId": "nm0136147"}, {"text": "I've waited too long already.", "character": "Elizabeth", "characterId": "nm0824489"}, {"text": "[goes down to where Nicholas is laying]\nAnd now, my dear Nicholas, I have you exactly as I want you - helpless.", "character": "Elizabeth", "characterId": "nm0824489"}, {"text": "Elizabeth, there is no time for this.", "character": "Doctor Leon", "characterId": "nm0136147"}, {"text": "I've waited an eternity for this moment. There has to be time. Is it not ironical, my dear husband, your wife an adultress, your mother an adultress, your uncle an adulterer, your closest friend an adulterer - do you not find that amusing, dear Nicholas?", "character": "Elizabeth", "characterId": "nm0824489"}, {"text": "Elizabeth.", "character": "Doctor Leon", "characterId": "nm0136147"}]}, {"lines": [{"text": "We will exhume Elizabeth.", "character": "Doctor Leon", "characterId": "nm0136147"}]}, {"lines": [{"text": "[last lines]", "character": null, "characterId": null}, {"text": "No one shall ever enter this room again.", "character": "Catherine", "characterId": "nm0026035"}]}, {"lines": [{"text": "Maximilian, we must break into the torture chamber! Quickly!", "character": "Catherine", "characterId": "nm0026035"}]}]}