{"quotes": [{"lines": [{"text": "Our law is She, the goddess, who's your god?", "character": "Taphir", "characterId": "nm0792506"}, {"text": "Our god? We don't have god, we do business.", "character": "Dick", "characterId": "nm0612078"}]}, {"lines": [{"text": "Your friend seems slightly overenthusiastic.", "character": "Pretty Boy", "characterId": "nm0104753"}, {"text": "My friend's an asshole.", "character": "Tom", "characterId": "nm0331563"}]}, {"lines": [{"text": "What's wrong?", "character": "She", "characterId": "nm0000922"}, {"text": "I don't know, but something is.", "character": "Tom", "characterId": "nm0331563"}]}, {"lines": [{"text": "What was that?", "character": "Dick", "characterId": "nm0612078"}, {"text": "A bomb.", "character": "She", "characterId": "nm0000922"}, {"text": "A what?", "character": "Dick", "characterId": "nm0612078"}, {"text": "A bomb!", "character": "She", "characterId": "nm0000922"}, {"text": "What's a bomb?", "character": "Dick", "characterId": "nm0612078"}]}, {"lines": [{"text": "What do you think?", "character": "Dick", "characterId": "nm0612078"}, {"text": "About what?", "character": "Tom", "characterId": "nm0331563"}, {"text": "Come on! You like her!", "character": "Dick", "characterId": "nm0612078"}, {"text": "Yeah, I do.", "character": "Tom", "characterId": "nm0331563"}]}, {"lines": [{"text": "You're not making any sense!", "character": "Shandra", "characterId": "nm0450375"}, {"text": "Shandra, this has nothing to do with sense.", "character": "She", "characterId": "nm0000922"}]}, {"lines": [{"text": "[after rescuing Shandra from being tortured on a rack]\nYou look a bit taller.", "character": "Dick", "characterId": "nm0612078"}]}]}