{"quotes": [{"lines": [{"text": "What in the hell are you doing with the poster of a penguin up in your room?", "character": "Carrie", "characterId": "nm0450242"}, {"text": "Oh god, I'm a penguin freak. I mean, what can I tell you? I mean, I just love those little fuckers.", "character": "Mitzi", "characterId": "nm0265517"}]}, {"lines": [{"text": "Sit down, John, leave me alone. I'm trying to speak for you. I'm trying to speak for all of you. I am the student body!", "character": "Carrie", "characterId": "nm0450242"}]}]}