{"quotes": [{"lines": [{"text": "When I'm worth forty million dollars, I'm going to have a secretary looks exactly like you.", "character": "Bob Regan", "characterId": "nm0639529"}, {"text": "Oh, my tastes are fairly simple. Twenty million would be quite enough.", "character": "Noel Faraday", "characterId": "nm0707048"}]}, {"lines": [{"text": "France fell in eighteen days, and you're not as tough as France.", "character": "Bob Regan", "characterId": "nm0639529"}]}, {"lines": [{"text": "How did he die?", "character": "Charles Murdock", "characterId": "nm0007995"}, {"text": "Protesting his innocence.", "character": "Andrew Colby", "characterId": "nm0001637"}]}, {"lines": [{"text": "How many doors and secretaries do you have to go through to get to see this guy?", "character": "Bob Regan", "characterId": "nm0639529"}, {"text": "Anything I can do for you?", "character": "Noel Faraday", "characterId": "nm0707048"}, {"text": "Any number of things but unfortunately I'm here on business. I want to see Mr Colby.", "character": "Bob Regan", "characterId": "nm0639529"}, {"text": "What did you want to see him about?", "character": "Noel Faraday", "characterId": "nm0707048"}, {"text": "Well he's been carrying on with my grandmother, I'd like to find out what his intentions are...", "character": "Bob Regan", "characterId": "nm0639529"}, {"text": "If you have any business with Mr Colby...", "character": "Noel Faraday", "characterId": "nm0707048"}, {"text": "I've lots of business but it's all personal.", "character": "Bob Regan", "characterId": "nm0639529"}, {"text": "I'm his secretary - his personal secretary.", "character": "Noel Faraday", "characterId": "nm0707048"}, {"text": "Well it just goes to show you how far a girl can get if she keeps her stockings' seams straight. Don't get up! I'll announce myself...", "character": "Bob Regan", "characterId": "nm0639529"}]}]}