{"quotes": [{"lines": [{"text": "Where are you going Battan?", "character": "Lincoln Costain", "characterId": "nm0001258"}, {"text": "Awe shucks, what's the use, I can't get the dang thing to work anyhow.", "character": "Booton 'Little Maca' MacAvoy", "characterId": "nm0790272"}, {"text": "In my outfit we don't quit until it's too dark to work or time to eat. I didn't hear the dinner bell - did you?", "character": "Lincoln Costain", "characterId": "nm0001258"}]}, {"lines": [{"text": "Mr. Bryson tells me it's impossible to load cattle onto boats in these waters.", "character": "Henrietta MacAvoy", "characterId": "nm0587256"}, {"text": "It was tried once on the big island two ships ran on reefs and there's no anchorage further out.", "character": "Calvin Bryson", "characterId": "nm0191685"}, {"text": "Don't they have docks in Alleah?", "character": "Lincoln Costain", "characterId": "nm0001258"}, {"text": "Never needed them.\"", "character": "Calvin Bryson", "characterId": "nm0191685"}, {"text": "Well how do they load then?", "character": "Lincoln Costain", "characterId": "nm0001258"}, {"text": "Mostly by long boat. Can you imagine trying to load cattle by long boat?", "character": "Calvin Bryson", "characterId": "nm0191685"}, {"text": "Well, there's got to be a way, there always is, it's just a matter of finding it.", "character": "Lincoln Costain", "characterId": "nm0001258"}, {"text": "Mr. Costain says there ain't never been a horse that ain't been rode and never been a rider that ain't been throwed.", "character": "Booton 'Little Maca' MacAvoy", "characterId": "nm0790272"}, {"text": "Well, I won't challenge the statement but I will the grammar.", "character": "Calvin Bryson", "characterId": "nm0191685"}, {"text": "Grammar never was my strong suit.", "character": "Lincoln Costain", "characterId": "nm0001258"}, {"text": "Young man you are sprouting up like a weed.", "character": "Calvin Bryson", "characterId": "nm0191685"}, {"text": "At least he's got good rock candy.", "character": "Lincoln Costain", "characterId": "nm0001258"}]}, {"lines": [{"text": "10,000 acres huh, that's a good size pea patch even where I come from.", "character": "Lincoln Costain", "characterId": "nm0001258"}, {"text": "Where's that?", "character": "Booton 'Little Maca' MacAvoy", "characterId": "nm0790272"}, {"text": "Texas. There you can ride a month in any direction and never touch a fence.", "character": "Lincoln Costain", "characterId": "nm0001258"}, {"text": "It must be beautiful.", "character": "Booton 'Little Maca' MacAvoy", "characterId": "nm0790272"}, {"text": "Oh, it is.", "character": "Lincoln Costain", "characterId": "nm0001258"}, {"text": "Costain, do you think you could ever like it here?", "character": "Booton 'Little Maca' MacAvoy", "characterId": "nm0790272"}, {"text": "No, no nah. This fruit bowl ain't for me. Some people might like it just fine, though.", "character": "Lincoln Costain", "characterId": "nm0001258"}, {"text": "Suppose you're going back to Texas huh?", "character": "Booton 'Little Maca' MacAvoy", "characterId": "nm0790272"}, {"text": "You bet", "character": "Lincoln Costain", "characterId": "nm0001258"}, {"text": "Got a wife there?", "character": "Booton 'Little Maca' MacAvoy", "characterId": "nm0790272"}, {"text": "Haven't met the woman who could afford me.", "character": "Lincoln Costain", "characterId": "nm0001258"}, {"text": "Then you never did have one.", "character": "Booton 'Little Maca' MacAvoy", "characterId": "nm0790272"}, {"text": "Nope, had the small pox once though, amounts to the same thing.", "character": "Lincoln Costain", "characterId": "nm0001258"}, {"text": "Yea, guess you never wanted to settle down with any woman no matter how nice they were huh.", "character": "Booton 'Little Maca' MacAvoy", "characterId": "nm0790272"}, {"text": "That's about right Yeah.", "character": "Lincoln Costain", "characterId": "nm0001258"}, {"text": "But you can't have kids if you ain't married.", "character": "Booton 'Little Maca' MacAvoy", "characterId": "nm0790272"}, {"text": "Yeh, ain't that a mercy?", "character": "Lincoln Costain", "characterId": "nm0001258"}, {"text": "What are you gonna you do when you get old?", "character": "Booton 'Little Maca' MacAvoy", "characterId": "nm0790272"}, {"text": "Die I guess.", "character": "Lincoln Costain", "characterId": "nm0001258"}, {"text": "I mean before that, who'll take care of you if you don't have a son?", "character": "Booton 'Little Maca' MacAvoy", "characterId": "nm0790272"}, {"text": "I'll say one thing for you - you get a notion you sure hang on to it, Burton.", "character": "Lincoln Costain", "characterId": "nm0001258"}, {"text": "Booton.", "character": "Booton 'Little Maca' MacAvoy", "characterId": "nm0790272"}, {"text": "Oh yeah.", "character": "Lincoln Costain", "characterId": "nm0001258"}]}, {"lines": [{"text": "Yes, it's true they do like their fun.", "character": "Henrietta MacAvoy", "characterId": "nm0587256"}, {"text": "They'd rather giggle than laugh, they'd rather laugh than eat they're like a bunch of kids out there. A school girl would be more sober mam'm.", "character": "Lincoln Costain", "characterId": "nm0001258"}]}, {"lines": [{"text": "What is it boy? What's the matter?", "character": "Lincoln Costain", "characterId": "nm0001258"}, {"text": "It's One of the animals, a big one he's eatin' up the vegetables again.", "character": "Booton 'Little Maca' MacAvoy", "characterId": "nm0790272"}, {"text": "Get out of there. Get out of my garden, do you hear me? Get out!", "character": "Henrietta MacAvoy", "characterId": "nm0587256"}, {"text": "One of the animals, woe doggey, you didn't tell me you had cattle around here, Button", "character": "Lincoln Costain", "characterId": "nm0001258"}, {"text": "Booton. We don't that thing's wild but I sure hope he eats the turnips!", "character": "Booton 'Little Maca' MacAvoy", "characterId": "nm0790272"}, {"text": "He may be wild but he ain't no thing. That's about a thousand pounds of prime bull out there.", "character": "Lincoln Costain", "characterId": "nm0001258"}, {"text": "You willful, worthless, misbegotten beast!", "character": "Henrietta MacAvoy", "characterId": "nm0587256"}, {"text": "That's a right nice vocabulary Ms. McEvoy but you'll never talk him out of there...", "character": "Lincoln Costain", "characterId": "nm0001258"}]}, {"lines": [{"text": "Where are they?", "character": "Lincoln Costain", "characterId": "nm0001258"}, {"text": "Boys not tell me, boss. Maybe they go work someplace else, yes?", "character": "Kimo", "characterId": "nm0876797"}, {"text": "Yeah, yeah, maybe it'll snow this afternoon too, but I doubt it.", "character": "Lincoln Costain", "characterId": "nm0001258"}]}, {"lines": [{"text": "You just can't expect to change a whole culture overnight.", "character": "Henrietta MacAvoy", "characterId": "nm0587256"}, {"text": "I don't have the least notion of changing it. If you'll just give me my wages I won't be troubling you any further.", "character": "Lincoln Costain", "characterId": "nm0001258"}, {"text": "You know, it is Sunday. They're entitled to some recreation.", "character": "Henrietta MacAvoy", "characterId": "nm0587256"}, {"text": "There just ain't any Sundays when it's roundup until the job gets done.", "character": "Lincoln Costain", "characterId": "nm0001258"}, {"text": "Well, maybe if you met them halfway they would be able...", "character": "Henrietta MacAvoy", "characterId": "nm0587256"}, {"text": "Ma'am there aren't any halfways in the cattle business. It would be easier to make a cherry pie out of barbed wire than to make a cowboy out of the best of the lot of them. They just ain't cut out for workin'.", "character": "Lincoln Costain", "characterId": "nm0001258"}, {"text": "Booton says they're really trying.", "character": "Henrietta MacAvoy", "characterId": "nm0587256"}, {"text": "That's whats so frightening, they are.", "character": "Lincoln Costain", "characterId": "nm0001258"}, {"text": "But if they're showing progress...", "character": "Henrietta MacAvoy", "characterId": "nm0587256"}, {"text": "They aren't showing progress, they're just trying. It ain't the same thing.", "character": "Lincoln Costain", "characterId": "nm0001258"}]}, {"lines": [{"text": "Hey, you know, I think I sold them boys short when I said they couldn't drive a hot nail in a snow bank. I think they could, I really think they could. Henrietta, what are you cryin' about?", "character": "Lincoln Costain", "characterId": "nm0001258"}, {"text": "I don't know, I guess I never really believed it would happen.", "character": "Henrietta MacAvoy", "characterId": "nm0587256"}, {"text": "You made a believer out of me, Costain. Mrs., here's your money. Coin of the realm. I'm offering a mate's pay for anyone who'll nursemaid those cows back to California...", "character": "Capt. Cary", "characterId": "nm0279786"}, {"text": "Well, that's my chance to get back to Texas. I don't know, Captain, that's right temptin' but I don't think I can leave Mrs. McEvoy with them pineapple cowboys. I mean they'd drive her dingy and I'm about the only one around who knows how to handle them.", "character": "Lincoln Costain", "characterId": "nm0001258"}, {"text": "Well, suit yourself, lad, and I don't blame you but I've got to get them cattle to California. Thank you, both of you.", "character": "Capt. Cary", "characterId": "nm0279786"}, {"text": "Good-bye. Then you are going to stay, at least for a while, Linc.", "character": "Henrietta MacAvoy", "characterId": "nm0587256"}, {"text": "Well for a while, yeah, for a while, you know,till they get the hang of it then I'm gonna get off this flower pot.", "character": "Lincoln Costain", "characterId": "nm0001258"}]}, {"lines": [{"text": "Mamma! Mamma!", "character": "Booton 'Little Maca' MacAvoy", "characterId": "nm0790272"}, {"text": "Good heavens, we're right here", "character": "Henrietta MacAvoy", "characterId": "nm0587256"}, {"text": "Tarnation Mamma I swam one of those critters out just as smooth as butter. Did you see?", "character": "Booton 'Little Maca' MacAvoy", "characterId": "nm0790272"}, {"text": "Of course we did, dear, and nobody could have done it better.", "character": "Henrietta MacAvoy", "characterId": "nm0587256"}, {"text": "Aww, well now that's a little thick don't you think? Ain't nobody gonna pin a rose on you just for doing your job. You remember that, Booton.", "character": "Lincoln Costain", "characterId": "nm0001258"}, {"text": "Ma, Ma, he called me by my right name! Did you hear him? He said it for the first time!", "character": "Booton 'Little Maca' MacAvoy", "characterId": "nm0790272"}]}]}