{"quotes": [{"lines": [{"text": "Say, Jack, she's so crooked they'll have to bury her in a trombone.", "character": "Jerry Burke", "characterId": "nm0888408"}]}, {"lines": [{"text": "Hey Jack, can't you fix me up a little drink?", "character": "Jerry Burke", "characterId": "nm0888408"}, {"text": "One more drink and you'll explode!", "character": "Jack", "characterId": "nm0770850"}, {"text": "Well, get me it and get outta the way.", "character": "Jerry Burke", "characterId": "nm0888408"}]}, {"lines": [{"text": "Look at the fun you're havin'!", "character": "Jerry Burke", "characterId": "nm0888408"}, {"text": "Oh, you call that fun? Playing Santa Claus to a lot of baby doll gold diggers.", "character": "Jack", "characterId": "nm0770850"}, {"text": "Oh, Jack, now they're all good little girls - every one of 'em.", "character": "Jerry Burke", "characterId": "nm0888408"}, {"text": "Oh, just an 18 carat sap. Any chump in the world would know what they're after.", "character": "Jack", "characterId": "nm0770850"}, {"text": "You insinuating that I'm a Sugar Daddy?", "character": "Jerry Burke", "characterId": "nm0888408"}]}, {"lines": [{"text": "Someday you'll be glad when the right man comes along.", "character": "Jack", "characterId": "nm0770850"}, {"text": "I know. That's what I try to tell myself. But, but most men won't have anything to do with a girl - with a girl that's good.", "character": "Daisy", "characterId": "nm0233390"}]}, {"lines": [{"text": "Oh, no kidding, I missed you so much, I started talkin' to your picture.", "character": "Mary", "characterId": "nm0522281"}, {"text": "That's nothing. I wrote poetry to you.", "character": "Jack", "characterId": "nm0770850"}, {"text": "You did? Let's see it!", "character": "Mary", "characterId": "nm0522281"}, {"text": "I tore it up.", "character": "Jack", "characterId": "nm0770850"}, {"text": "Oh, why?", "character": "Mary", "characterId": "nm0522281"}, {"text": "For no rhyme or reason.", "character": "Jack", "characterId": "nm0770850"}]}, {"lines": [{"text": "white, cool and nice.", "character": "Jack", "characterId": "nm0770850"}, {"text": "Oh, thanks.", "character": "Mary", "characterId": "nm0522281"}, {"text": "Some women are like red roses.", "character": "Jack", "characterId": "nm0770850"}, {"text": "Yeah, well, you look out for those red roses, they have thorns you know.", "character": "Mary", "characterId": "nm0522281"}]}, {"lines": [{"text": "Just for that I'm gonna give you a little kiss.", "character": "Jack", "characterId": "nm0770850"}, {"text": "Why a little one?", "character": "Mary", "characterId": "nm0522281"}]}, {"lines": [{"text": "You know, Mary, I'd be a good dancer if it wasn't for my feet.", "character": "Jerry Burke", "characterId": "nm0888408"}]}, {"lines": [{"text": "Say, waiter, bring me the bad news, please.", "character": "Jerry Burke", "characterId": "nm0888408"}, {"text": "Oh, are we going already?", "character": "Mary", "characterId": "nm0522281"}]}, {"lines": [{"text": "Say, lay off me or I'll smack you so hard you'd think you were kissed by a million John Gilberts.", "character": "Jerry Burke", "characterId": "nm0888408"}]}, {"lines": [{"text": "Whenever I get blue and discouraged, I just think of the wonderful advice you gave me on the train.", "character": "Daisy", "characterId": "nm0233390"}, {"text": "That's the spirit! Don't let 'em whip ya!", "character": "Jack", "characterId": "nm0770850"}]}, {"lines": [{"text": "No, I'm not crazy, but, you are! You'd have to be to ditch a little gal like Mary and run around with that dizzy blonde sharpshooter.", "character": "Jerry Burke", "characterId": "nm0888408"}]}, {"lines": [{"text": "Listen, chisler, I'm hep to you.", "character": "Jerry Burke", "characterId": "nm0888408"}, {"text": "Oh, so you're a smart guy, huh?", "character": "Daisy", "characterId": "nm0233390"}, {"text": "I don't have to be smart to get wise to a gal like you.", "character": "Jerry Burke", "characterId": "nm0888408"}]}, {"lines": [{"text": "Say, Jack, I'd lay off that porcupine - she's full of needles!", "character": "Jerry Burke", "characterId": "nm0888408"}]}, {"lines": [{"text": "Oh, tell me you love me and you do as I ask.", "character": "Daisy", "characterId": "nm0233390"}]}, {"lines": [{"text": "Thanks Jack. Now everything's KO.", "character": "Jerry Burke", "characterId": "nm0888408"}]}]}