{"quotes": [{"lines": [{"text": "Whatever became of Frances Bilky?", "character": "Norah Porter", "characterId": "nm0456533"}, {"text": "I don't know. She married a colonel, I think. Maybe it was a general. At any rate, she outranks all of us.", "character": "Captain Bill Hodges", "characterId": "nm0000851"}, {"text": "But that's wonderful! Now she'll have her lifelong ambition to lead the cotillion. Well, I guess that's what I always wanted too.", "character": "Norah Porter", "characterId": "nm0456533"}, {"text": "You don't have anything like that around here, do you, Captain?", "character": "Captain Bill Hodges", "characterId": "nm0000851"}, {"text": "Oh, I don't know. The Indians come down once a month and dance for us.", "character": "Captain David Porter", "characterId": "nm0000068"}]}, {"lines": [{"text": "I'm afraid you hurt Mr. Balfour's feelings.", "character": "Norah Porter", "characterId": "nm0456533"}, {"text": "To do that I'd have to kick him in the pocketbook.", "character": "Captain Bill Hodges", "characterId": "nm0000851"}]}]}