{"quotes": [{"lines": [{"text": "[to Rolls Royce]\nHow long since you had the body washed and polishd?", "character": "'Feathers' McCoy", "characterId": "nm0107574"}]}, {"lines": [{"text": "[Referring to Rolls Royce]\nLook at him - Cost me a thousand - Looks like a million.", "character": "'Bull' Weed", "characterId": "nm0051628"}]}, {"lines": [{"text": "-There was something I had to find out - - and that hour was worth more to me than my whole life.", "character": "'Bull' Weed", "characterId": "nm0051628"}]}]}