{"quotes": [{"lines": [{"text": "Have you heard of some fellas, who first came over to this country? You know what they found? They found a howling wilderness, with summers to hot, and winters freezing. Did they have insurance for their old age, for their crops, for their homes? They did not. They looked at the land and the forest and the rivers they looked at their wives, their kids, and their houses. Then they looked up at the sky and said thanks God, we'll take it from here. They were men!", "character": "Rusty", "characterId": "nm0000078"}]}]}